cnm_systems/__init__.py
cnm_systems/admin.py
cnm_systems/apps.py
cnm_systems/example.py
cnm_systems/models.py
cnm_systems/urls.py
cnm_systems/migrations/0001_initial.py
cnm_systems/migrations/__init__.py
cnm_systems/services/__init__.py
cnm_systems/services/email.py
cnm_systems-1.0.4.dist-info/DESCRIPTION.rst
cnm_systems-1.0.4.dist-info/METADATA
cnm_systems-1.0.4.dist-info/RECORD
cnm_systems-1.0.4.dist-info/WHEEL
cnm_systems-1.0.4.dist-info/metadata.json
cnm_systems-1.0.4.dist-info/top_level.txt
