Metadata-Version: 2.0
Name: cnm-systems
Version: 1.0.4
Summary: System of Cinnamon
Home-page: https://github.com/hieutrieu/systems
Author: Andrew Carnegie
Author-email: mrhieutrieu@gmail.com
License: BSD
Keywords: development
Platform: UNKNOWN
Classifier: License :: OSI Approved :: MIT License
Classifier: Framework :: Django
Classifier: Programming Language :: Python :: 3
Classifier: Programming Language :: Python :: 3.5
Requires-Dist: django-ckeditor
Requires-Dist: emails
